lunar_policy/.py.typed
lunar_policy/__init__.py
lunar_policy/check.py
lunar_policy/node.py
lunar_policy/nodepath.py
lunar_policy/nodepath_parser.py
lunar_policy/result.py
lunar_policy/variables.py
lunar_policy-0.2.2.dist-info/METADATA
lunar_policy-0.2.2.dist-info/WHEEL
lunar_policy-0.2.2.dist-info/licenses/LICENSE
lunar_policy-0.2.2.dist-info/RECORD
