Metadata-Version: 2.4
Name: lunar_policy
Version: 0.2.2
Summary: Lunar Policy SDK
Project-URL: homepage, https://earthly.dev
Project-URL: repository, https://github.com/earthly/egov
License-File: LICENSE
Classifier: Development Status :: 2 - Pre-Alpha
Classifier: Intended Audience :: Developers
Classifier: License :: OSI Approved :: Mozilla Public License 2.0 (MPL 2.0)
Classifier: Operating System :: OS Independent
Classifier: Programming Language :: Python :: 3.9
Requires-Python: >=3.9
